lib_collection/__init__.py
lib_collection/node.py
lib_collection/kvstore/__init__.py
lib_collection/kvstore/hash_map.py
lib_collection/kvstore/linked_list.py
lib_collection/queue/__init__.py
lib_collection/queue/array_queue.py
lib_collection/queue/fixed_capacity_array_queue.py
lib_collection/queue/linked_queue.py
lib_collection/queue/resizing_array_queue.py
lib_collection/queue/simple_linked_queue.py
lib_collection/search/__init__.py
lib_collection/search/binary_search_kvstore.py
lib_collection/search/hash_map.py
lib_collection/search/linear_probing_kvstore.py
lib_collection/search/linked_list.py
lib_collection/search/separate_chaining_hash_map.py
lib_collection/search/sequential_search_kvstore.py
lib_collection/stack/__init__.py
lib_collection/stack/linked_stack.py
lib_collection/stack/resizing_array_stack.py
xy_libcollection-0.1.6.dist-info/LICENSE
xy_libcollection-0.1.6.dist-info/METADATA
xy_libcollection-0.1.6.dist-info/WHEEL
xy_libcollection-0.1.6.dist-info/top_level.txt
xy_libcollection-0.1.6.dist-info/RECORD
