Metadata-Version: 2.1
Name: xy-libcollection
Version: 0.1.6
Summary: xueyan's collection libs
Home-page: https://github.com/qimiaoxue/libcollection
Author: xueyan
Author-email: xueyan0407@outlook.com
License: UNKNOWN
Platform: UNKNOWN
